causalpfn/__init__.py
causalpfn/causal_estimator.py
causalpfn/evaluation.py
causalpfn/utils.py
causalpfn/models/__init__.py
causalpfn/models/icl_model.py
causalpfn/models/loading.py
causalpfn/models/model.py
causalpfn/models/transformer_layer.py
causalpfn/models/utils.py
causalpfn-0.1.4.dist-info/licenses/LICENSE
causalpfn-0.1.4.dist-info/METADATA
causalpfn-0.1.4.dist-info/WHEEL
causalpfn-0.1.4.dist-info/top_level.txt
causalpfn-0.1.4.dist-info/RECORD
