Metadata-Version: 2.4
Name: causalpfn
Version: 0.1.4
Summary: Amortized Causal Effect Estimation via In-Context Learning
Author-email: Vahid Balazadeh <balazadehvahid@gmail.com>, Hamidreza Kamkari <hamidrezakamkari@gmail.com>
License:                                  CausalPFN License
Requires-Python: >=3.10
License-File: LICENSE
Requires-Dist: torch>=2.0
Requires-Dist: numpy>=1.24
Requires-Dist: tqdm
Requires-Dist: faiss-cpu>=1.9.0
Requires-Dist: scikit-learn>=1.5.2
Requires-Dist: huggingface_hub
Provides-Extra: dev
Requires-Dist: torch==2.3.1; extra == "dev"
Requires-Dist: numpy==1.26.4; extra == "dev"
Requires-Dist: scikit-learn==1.5.2; extra == "dev"
Requires-Dist: econml==0.15.1; extra == "dev"
Requires-Dist: huggingface_hub==0.32.4; extra == "dev"
Requires-Dist: tqdm==4.67.1; extra == "dev"
Requires-Dist: faiss-cpu==1.9.0; extra == "dev"
Requires-Dist: pytest==8.4.0; extra == "dev"
Requires-Dist: black==25.1.0; extra == "dev"
Requires-Dist: isort==6.0.1; extra == "dev"
Requires-Dist: jupyter==1.1.1; extra == "dev"
Requires-Dist: ipython==8.37.0; extra == "dev"
Requires-Dist: pandas==2.3.0; extra == "dev"
Requires-Dist: pytest-cov==6.1.1; extra == "dev"
Requires-Dist: matplotlib==3.10.3; extra == "dev"
Requires-Dist: scikit-uplift==0.5.1; extra == "dev"
Requires-Dist: python-dotenv==1.1.0; extra == "dev"
Requires-Dist: FLAML[automl]==2.3.5; extra == "dev"
Dynamic: license-file
